<annotation>
	<folder>VOC2008</folder>
	<filename>2008_000826.jpg</filename>
	<source>
		<database>The VOC2008 Database</database>
		<annotation>PASCAL VOC2008</annotation>
		<image>flickr</image>
		<flickrid>n/a</flickrid>
	</source>
	<owner>
		<flickrid>n/a</flickrid>
		<name>n/a</name>
	</owner>
	<size>
		<width>400</width>
		<height>350</height>
		<depth>3</depth>
	</size>
	<segmented>0</segmented>
	<object>
		<name>person</name>
		<bndbox>
			<xmin>207.906</xmin>
			<ymin>109.188</ymin>
			<xmax>269.8718</xmax>
			<ymax>310.8974</ymax>
		</bndbox>
	</object>
	<object>
		<name>person</name>
		<bndbox>
			<xmin>154.0598</xmin>
			<ymin>102.3504</ymin>
			<xmax>217.735</xmax>
			<ymax>311.7521</ymax>
		</bndbox>
	</object>
</annotation>
